Metadata-Version: 1.1
Name: rotten-bites
Version: 1.0.0
Summary: A tool for detecting bit rot in files.
Home-page: https://github.com/philipbl/rotten_bites
Author: Philip Lundrigan
Author-email: philipbl@cs.utah.edu
License: MIT License
Download-URL: https://github.com/philipbl/rotten_bites/archive/1.0.0.zip
Platform: UNKNOWN
Classifier: Intended Audience :: End Users/Desktop
Classifier: Intended Audience :: Developers
Classifier: License :: OSI Approved :: MIT License
Classifier: Operating System :: OS Independent
Classifier: Programming Language :: Python :: 3.4
